backbones/__init__.py
backbones/mobilenetv2.py
backbones/resnet.py
backbones/vit.py
paddletransfer/__init__.py
paddletransfer/finetuning/__init__.py
paddletransfer/finetuning/img_cls/__init__.py
paddletransfer/finetuning/img_cls/base.py
paddletransfer/finetuning/img_cls/bss.py
paddletransfer/finetuning/img_cls/cot.py
paddletransfer/finetuning/img_cls/delta.py
paddletransfer/finetuning/img_cls/l2sp.py
paddletransfer/finetuning/img_cls/mmd.py
paddletransfer/finetuning/img_cls/rifle.py
paddletransfer-0.1.0.dist-info/LICENSE
paddletransfer-0.1.0.dist-info/METADATA
paddletransfer-0.1.0.dist-info/WHEEL
paddletransfer-0.1.0.dist-info/top_level.txt
paddletransfer-0.1.0.dist-info/RECORD
