Metadata-Version: 2.1
Name: paddletransfer
Version: 0.1.0
Summary: transfer learning toolkits for finetune deep learning models
Author: Baidu-BDL
Author-email: autodl@baidu.com
License: Apache 2.0
Keywords: transfer learning toolkits for paddle models
Platform: UNKNOWN
Classifier: Development Status :: 4 - Beta
Classifier: Intended Audience :: Developers
Classifier: Programming Language :: Python :: 3.9
Requires-Python: >=3.7
License-File: LICENSE
Requires-Dist: numpy
